solvis_api_evaluations/__init__.py
solvis_api_evaluations/get_devices.py
solvis_api_evaluations/get_evaluations.py
solvis_api_evaluations/get_questionnaire.py
solvis_api_evaluations/get_surveyed_units.py
solvis_api_evaluations/get_suspicious_occurrences.py
solvis_api_evaluations/process_evaluations.py
solvis_api_evaluations-0.1.5.dist-info/METADATA
solvis_api_evaluations-0.1.5.dist-info/WHEEL
solvis_api_evaluations-0.1.5.dist-info/licenses/LICENSE
solvis_api_evaluations-0.1.5.dist-info/RECORD
